libsg/__init__.py
libsg/api.py
libsg/app.py
libsg/arch.py
libsg/arch_builder.py
libsg/assets.py
libsg/geo.py
libsg/io.py
libsg/object_placement.py
libsg/object_suggestor.py
libsg/scene.py
libsg/scene_builder.py
libsg/scene_types.py
libsg/simscene.py
libsg/simulator.py
libsg/test_simulator.py
libsg/vhacd/__init__.py
libsg-0.0.1rc7.dist-info/LICENSE
libsg-0.0.1rc7.dist-info/METADATA
libsg-0.0.1rc7.dist-info/WHEEL
libsg-0.0.1rc7.dist-info/top_level.txt
libsg-0.0.1rc7.dist-info/RECORD
