Metadata-Version: 2.1
Name: libsg
Version: 0.0.1rc7
Summary: libSG: Scene Generation Library
Home-page: https://github.com/3dlg-hcvc/scene-builder
Author: 3dlg-hcvc
Author-email: Manolis Savva <manolis.savva@gmail.com>
Project-URL: Homepage, https://github.com/3dlg-hcvc/scene-builder
Project-URL: Bug Tracker, https://github.com/3dlg-hcvc/scene-builder/issues
Classifier: Programming Language :: Python :: 3
Classifier: License :: OSI Approved :: MIT License
Classifier: Operating System :: OS Independent
Requires-Python: >=3.9
License-File: LICENSE
Requires-Dist: easydict
Requires-Dist: flask
Requires-Dist: numpy
Requires-Dist: pybullet
Requires-Dist: pysolr
Requires-Dist: scipy
